CHANGES.txt
LICENSE.txt
MANIFEST.in
README.txt
setup.py
PyroMP/Qt.py
PyroMP/__init__.py
PyroMP/callback.py
PyroMP/errors.py
PyroMP/log_server.py
PyroMP/queued_service.py
PyroMP/server.py
PyroMP/service.py
PyroMP/version.py
PyroMP.egg-info/PKG-INFO
PyroMP.egg-info/SOURCES.txt
PyroMP.egg-info/dependency_links.txt
PyroMP.egg-info/requires.txt
PyroMP.egg-info/top_level.txt
PyroMP/examples/callbacks_events/callback_object.py
PyroMP/examples/callbacks_events/callback_service.py
PyroMP/examples/callbacks_events/queued_callback.py
PyroMP/examples/local_service/local_service.py
PyroMP/examples/plotting/matplotlib_example.py
PyroMP/examples/plotting/pyqtgraph_example.py
PyroMP/examples/pyside_pyqt_combination/pyqt_service.py
PyroMP/examples/pyside_pyqt_combination/pyside_service.py
PyroMP/examples/qt_service/log_window.py
PyroMP/examples/qt_service/qt_service.py
PyroMP/examples/queued_service/queued_service.py
PyroMP/examples/warehouse/phase1/person.py
PyroMP/examples/warehouse/phase1/visit.py
PyroMP/examples/warehouse/phase1/warehouse.py
PyroMP/examples/warehouse/phase2/person.py
PyroMP/examples/warehouse/phase2/visit.py
PyroMP/examples/warehouse/phase2/warehouse.py
PyroMP/examples/warehouse/phase3/another_visit.py
PyroMP/examples/warehouse/phase3/person.py
PyroMP/examples/warehouse/phase3/visit.py
PyroMP/examples/warehouse/phase3/warehouse.py
PyroMP/tests/__init__.py
PyroMP/tests/callback_tests.py
PyroMP/tests/callback_with_another_service_tests.py
PyroMP/tests/callback_with_qt_service_tests.py
PyroMP/tests/log_server_tests.py
PyroMP/tests/nameserver_tests.py
PyroMP/tests/qt_service_tests.py
PyroMP/tests/queued_callback_tests.py
PyroMP/tests/queued_service_tests.py
PyroMP/tests/service_in_thread_tests.py
PyroMP/tests/service_multiplexed_tests.py
PyroMP/tests/service_tests.py