Metadata-Version: 1.0
Name: PyroMP
Version: 1.0
Summary: Easy muliprocessing combining Pyro4 and the built-in multiprocessing module
Home-page: https://bitbucket.org/PBrimmers/PyroMP
Author: Philipp Brimmers
Author-email: P.Brimmers@yahoo.de
License: Copyright (c) 2014, Philipp Brimmers
